jstr/__init__.py
jstr/_modidx.py
jstr/_tmp.py
jstr/core.py
jstr-0.0.4.dist-info/LICENSE
jstr-0.0.4.dist-info/METADATA
jstr-0.0.4.dist-info/WHEEL
jstr-0.0.4.dist-info/entry_points.txt
jstr-0.0.4.dist-info/top_level.txt
jstr-0.0.4.dist-info/RECORD
