Metadata-Version: 2.1
Name: jstr
Version: 0.0.4
Summary: jstr (join / just strings)
Home-page: https://github.com/dsm-72/jstr
Author: dsm-72
Author-email: sumner.magruder@yale.edu
License: Apache Software License 2.0
Keywords: j str jstr join just strings dash dot underscore vargs
Classifier: Development Status :: 4 - Beta
Classifier: Intended Audience :: Developers
Classifier: Natural Language :: English
Classifier: Programming Language :: Python :: 3.11
Classifier: License :: OSI Approved :: Apache Software License
Requires-Python: >=3.11
License-File: LICENSE
Requires-Dist: nchr
Requires-Dist: nlit
Requires-Dist: atup
Provides-Extra: dev
